map_uk/__init__.py
map_uk/constants.py
map_uk/geojson/__init__.py
map_uk/geojson/getter.py
map_uk/geojson/simplifier.py
map_uk/map/__init__.py
map_uk/map/base.py
map_uk/map/choropleth.py
map_uk/map/map.py
map_uk/utils/__init__.py
map_uk/utils/file_downloader.py
map_uk/utils/file_unizpper.py
map_uk-0.0.0.dist-info/METADATA
map_uk-0.0.0.dist-info/WHEEL
map_uk-0.0.0.dist-info/RECORD
