Metadata-Version: 2.1
Name: map-uk
Version: 0.0.0
Summary: Quickly create maps of the UK in Python
Home-page: https://github.com/jap546/map-uk
Author: Jordan Pinder
Author-email: jordan.pinder.dev@gmail.com
Requires-Python: >=3.9,<3.12
Classifier: Programming Language :: Python :: 3
Classifier: Programming Language :: Python :: 3.9
Classifier: Programming Language :: Python :: 3.10
Classifier: Programming Language :: Python :: 3.11
Requires-Dist: folium (>=0.15.0,<0.16.0)
Requires-Dist: geopandas (>=0.14.1,<0.15.0)
Requires-Dist: jenkspy (>=0.4.0,<0.5.0)
Requires-Dist: pandas (>=2.1.3,<3.0.0)
Requires-Dist: requests (>=2.31.0,<3.0.0)
Requires-Dist: topojson (>=1.7,<2.0)
Requires-Dist: tqdm (>=4.66.1,<5.0.0)
Project-URL: Repository, https://github.com/jap546/map-uk
